{"nodes": [{"id": "sqs_encryption_sse_sqs", "label": "SSE-SQS (SQS-managed keys)", "file_type": "concept", "source_file": "docs/17-gap-fill/sqs-encryption/sse.md", "source_location": null, "source_url": "https://docs.aws.amazon.com/AWSSimpleQueueService/latest/SQSDeveloperGuide/sqs-server-side-encryption.html", "captured_at": null, "author": null, "contributor": null}, {"id": "sqs_encryption_sse_kms", "label": "SSE-KMS (AWS KMS keys)", "file_type": "concept", "source_file": "docs/17-gap-fill/sqs-encryption/sse.md", "source_location": null, "source_url": "https://docs.aws.amazon.com/AWSSimpleQueueService/latest/SQSDeveloperGuide/sqs-server-side-encryption.html", "captured_at": null, "author": null, "contributor": null}, {"id": "sqs_encryption_data_key", "label": "Data key (DEK)", "file_type": "concept", "source_file": "docs/17-gap-fill/sqs-encryption/sse.md", "source_location": null, "source_url": "https://docs.aws.amazon.com/AWSSimpleQueueService/latest/SQSDeveloperGuide/sqs-server-side-encryption.html", "captured_at": null, "author": null, "contributor": null}, {"id": "sqs_encryption_envelope_encryption", "label": "Envelope encryption", "file_type": "concept", "source_file": "docs/17-gap-fill/sqs-encryption/sse.md", "source_location": null, "source_url": "https://docs.aws.amazon.com/AWSSimpleQueueService/latest/SQSDeveloperGuide/sqs-server-side-encryption.html", "captured_at": null, "author": null, "contributor": null}, {"id": "sqs_encryption_data_key_reuse_period", "label": "Data key reuse period", "file_type": "concept", "source_file": "docs/17-gap-fill/sqs-encryption/sse.md", "source_location": null, "source_url": "https://docs.aws.amazon.com/AWSSimpleQueueService/latest/SQSDeveloperGuide/sqs-server-side-encryption.html", "captured_at": null, "author": null, "contributor": null}, {"id": "sqs_encryption_encryption_scope", "label": "Encryption scope (message body only)", "file_type": "concept", "source_file": "docs/17-gap-fill/sqs-encryption/sse.md", "source_location": null, "source_url": "https://docs.aws.amazon.com/AWSSimpleQueueService/latest/SQSDeveloperGuide/sqs-server-side-encryption.html", "captured_at": null, "author": null, "contributor": null}], "edges": [{"source": "sqs_encryption_sse_sqs", "target": "research_catalog_sqs", "relation": "implements", "confidence": "EXTRACTED", "confidence_score": 1.0, "source_file": "docs/17-gap-fill/sqs-encryption/sse.md", "source_location": null, "weight": 1.0}, {"source": "sqs_encryption_sse_kms", "target": "research_catalog_sqs", "relation": "implements", "confidence": "EXTRACTED", "confidence_score": 1.0, "source_file": "docs/17-gap-fill/sqs-encryption/sse.md", "source_location": null, "weight": 1.0}, {"source": "sqs_encryption_data_key", "target": "research_catalog_sqs", "relation": "conceptually_related_to", "confidence": "EXTRACTED", "confidence_score": 1.0, "source_file": "docs/17-gap-fill/sqs-encryption/sse.md", "source_location": null, "weight": 1.0}, {"source": "sqs_encryption_envelope_encryption", "target": "research_catalog_sqs", "relation": "conceptually_related_to", "confidence": "EXTRACTED", "confidence_score": 1.0, "source_file": "docs/17-gap-fill/sqs-encryption/sse.md", "source_location": null, "weight": 1.0}, {"source": "sqs_encryption_data_key_reuse_period", "target": "research_catalog_sqs", "relation": "conceptually_related_to", "confidence": "EXTRACTED", "confidence_score": 1.0, "source_file": "docs/17-gap-fill/sqs-encryption/sse.md", "source_location": null, "weight": 1.0}, {"source": "sqs_encryption_encryption_scope", "target": "research_catalog_sqs", "relation": "conceptually_related_to", "confidence": "EXTRACTED", "confidence_score": 1.0, "source_file": "docs/17-gap-fill/sqs-encryption/sse.md", "source_location": null, "weight": 1.0}, {"source": "research_catalog_sqs", "target": "research_catalog_sns_eventbridge", "relation": "references", "confidence": "EXTRACTED", "confidence_score": 1.0, "source_file": "docs/17-gap-fill/sqs-encryption/sse.md", "source_location": null, "weight": 1.0}, {"source": "sqs_encryption_encryption_scope", "target": "research_catalog_dlq", "relation": "references", "confidence": "EXTRACTED", "confidence_score": 1.0, "source_file": "docs/17-gap-fill/sqs-encryption/sse.md", "source_location": null, "weight": 1.0}], "hyperedges": []}