{"nodes": [{"id": "dask_overview_futures", "label": "Dask Futures", "file_type": "concept", "source_file": "docs/08-container-batch/dask/overview.md", "source_location": null, "source_url": null, "captured_at": null, "author": null, "contributor": null}, {"id": "dask_overview_task_graph", "label": "Task Graph", "file_type": "concept", "source_file": "docs/08-container-batch/dask/overview.md", "source_location": null, "source_url": null, "captured_at": null, "author": null, "contributor": null}, {"id": "dask_overview_distributed_scheduler", "label": "Distributed Scheduler and LocalCluster", "file_type": "concept", "source_file": "docs/08-container-batch/dask/overview.md", "source_location": null, "source_url": null, "captured_at": null, "author": null, "contributor": null}, {"id": "dask_overview_dataframe", "label": "Dask DataFrame", "file_type": "concept", "source_file": "docs/08-container-batch/dask/overview.md", "source_location": null, "source_url": null, "captured_at": null, "author": null, "contributor": null}, {"id": "dask_overview_delayed", "label": "Dask Delayed", "file_type": "concept", "source_file": "docs/08-container-batch/dask/overview.md", "source_location": null, "source_url": null, "captured_at": null, "author": null, "contributor": null}], "edges": [{"source": "dask_overview_futures", "target": "research_catalog_dask", "relation": "implements", "confidence": "EXTRACTED", "confidence_score": 1.0, "source_file": "docs/08-container-batch/dask/overview.md", "source_location": null, "weight": 1.0}, {"source": "dask_overview_task_graph", "target": "research_catalog_dask", "relation": "implements", "confidence": "EXTRACTED", "confidence_score": 1.0, "source_file": "docs/08-container-batch/dask/overview.md", "source_location": null, "weight": 1.0}, {"source": "dask_overview_distributed_scheduler", "target": "research_catalog_dask", "relation": "implements", "confidence": "EXTRACTED", "confidence_score": 1.0, "source_file": "docs/08-container-batch/dask/overview.md", "source_location": null, "weight": 1.0}, {"source": "dask_overview_dataframe", "target": "research_catalog_dask", "relation": "implements", "confidence": "EXTRACTED", "confidence_score": 1.0, "source_file": "docs/08-container-batch/dask/overview.md", "source_location": null, "weight": 1.0}, {"source": "dask_overview_delayed", "target": "research_catalog_dask", "relation": "implements", "confidence": "EXTRACTED", "confidence_score": 1.0, "source_file": "docs/08-container-batch/dask/overview.md", "source_location": null, "weight": 1.0}, {"source": "dask_overview_dataframe", "target": "research_catalog_apache_spark", "relation": "references", "confidence": "EXTRACTED", "confidence_score": 1.0, "source_file": "docs/08-container-batch/dask/overview.md", "source_location": null, "weight": 1.0}, {"source": "research_catalog_dask", "target": "research_catalog_htcondor_slurm", "relation": "references", "confidence": "EXTRACTED", "confidence_score": 1.0, "source_file": "docs/08-container-batch/dask/overview.md", "source_location": null, "weight": 1.0}], "hyperedges": []}