{"nodes": [{"id": "k8s_rbac_overview_role", "label": "Role (namespaced permission set)", "file_type": "concept", "source_file": "docs/17-gap-fill/k8s-rbac/overview.md", "source_location": null, "source_url": "https://kubernetes.io/docs/reference/access-authn-authz/rbac/", "captured_at": null, "author": null, "contributor": null}, {"id": "k8s_rbac_overview_clusterrole", "label": "ClusterRole (cluster-scoped permission set)", "file_type": "concept", "source_file": "docs/17-gap-fill/k8s-rbac/overview.md", "source_location": null, "source_url": null, "captured_at": null, "author": null, "contributor": null}, {"id": "k8s_rbac_overview_rolebinding", "label": "RoleBinding", "file_type": "concept", "source_file": "docs/17-gap-fill/k8s-rbac/overview.md", "source_location": null, "source_url": null, "captured_at": null, "author": null, "contributor": null}, {"id": "k8s_rbac_overview_clusterrolebinding", "label": "ClusterRoleBinding", "file_type": "concept", "source_file": "docs/17-gap-fill/k8s-rbac/overview.md", "source_location": null, "source_url": null, "captured_at": null, "author": null, "contributor": null}, {"id": "k8s_rbac_overview_verbs_rules", "label": "Verbs and rules (resources + apiGroups)", "file_type": "concept", "source_file": "docs/17-gap-fill/k8s-rbac/overview.md", "source_location": null, "source_url": null, "captured_at": null, "author": null, "contributor": null}, {"id": "k8s_rbac_overview_subjects", "label": "Subjects (users, groups, service accounts)", "file_type": "concept", "source_file": "docs/17-gap-fill/k8s-rbac/overview.md", "source_location": null, "source_url": null, "captured_at": null, "author": null, "contributor": null}, {"id": "k8s_rbac_overview_service_account_permissions", "label": "ServiceAccount permissions", "file_type": "concept", "source_file": "docs/17-gap-fill/k8s-rbac/overview.md", "source_location": null, "source_url": null, "captured_at": null, "author": null, "contributor": null}, {"id": "k8s_rbac_overview_privilege_escalation_prevention", "label": "Privilege escalation prevention", "file_type": "concept", "source_file": "docs/17-gap-fill/k8s-rbac/overview.md", "source_location": null, "source_url": null, "captured_at": null, "author": null, "contributor": null}], "edges": [{"source": "k8s_rbac_overview_role", "target": "research_catalog_kubernetes_jobs_cronjobs", "relation": "conceptually_related_to", "confidence": "EXTRACTED", "confidence_score": 1.0, "source_file": "docs/17-gap-fill/k8s-rbac/overview.md", "source_location": null, "weight": 1.0}, {"source": "k8s_rbac_overview_clusterrole", "target": "research_catalog_kubernetes_jobs_cronjobs", "relation": "conceptually_related_to", "confidence": "EXTRACTED", "confidence_score": 1.0, "source_file": "docs/17-gap-fill/k8s-rbac/overview.md", "source_location": null, "weight": 1.0}, {"source": "k8s_rbac_overview_rolebinding", "target": "research_catalog_kubernetes_jobs_cronjobs", "relation": "conceptually_related_to", "confidence": "EXTRACTED", "confidence_score": 1.0, "source_file": "docs/17-gap-fill/k8s-rbac/overview.md", "source_location": null, "weight": 1.0}, {"source": "k8s_rbac_overview_clusterrolebinding", "target": "research_catalog_kubernetes_jobs_cronjobs", "relation": "conceptually_related_to", "confidence": "EXTRACTED", "confidence_score": 1.0, "source_file": "docs/17-gap-fill/k8s-rbac/overview.md", "source_location": null, "weight": 1.0}, {"source": "k8s_rbac_overview_verbs_rules", "target": "research_catalog_kubernetes_jobs_cronjobs", "relation": "conceptually_related_to", "confidence": "EXTRACTED", "confidence_score": 1.0, "source_file": "docs/17-gap-fill/k8s-rbac/overview.md", "source_location": null, "weight": 1.0}, {"source": "k8s_rbac_overview_subjects", "target": "research_catalog_kubernetes_jobs_cronjobs", "relation": "conceptually_related_to", "confidence": "EXTRACTED", "confidence_score": 1.0, "source_file": "docs/17-gap-fill/k8s-rbac/overview.md", "source_location": null, "weight": 1.0}, {"source": "k8s_rbac_overview_service_account_permissions", "target": "research_catalog_kubernetes_jobs_cronjobs", "relation": "conceptually_related_to", "confidence": "EXTRACTED", "confidence_score": 1.0, "source_file": "docs/17-gap-fill/k8s-rbac/overview.md", "source_location": null, "weight": 1.0}, {"source": "k8s_rbac_overview_privilege_escalation_prevention", "target": "research_catalog_kubernetes_jobs_cronjobs", "relation": "conceptually_related_to", "confidence": "EXTRACTED", "confidence_score": 1.0, "source_file": "docs/17-gap-fill/k8s-rbac/overview.md", "source_location": null, "weight": 1.0}, {"source": "k8s_rbac_overview_rolebinding", "target": "k8s_rbac_overview_role", "relation": "references", "confidence": "EXTRACTED", "confidence_score": 1.0, "source_file": "docs/17-gap-fill/k8s-rbac/overview.md", "source_location": null, "weight": 1.0}, {"source": "k8s_rbac_overview_rolebinding", "target": "k8s_rbac_overview_subjects", "relation": "references", "confidence": "EXTRACTED", "confidence_score": 1.0, "source_file": "docs/17-gap-fill/k8s-rbac/overview.md", "source_location": null, "weight": 1.0}], "hyperedges": []}